py2tf/__init__.py
py2tf/_version.py
py2tf/cli.py
py2tf/validators.py
py2tf/converters/__init__.py
py2tf/converters/jinja.py
py2tf/converters/markdown.py
py2tf/templates/__init__.py
py2tf/templates/hcl.tf
py2tf/templates/module_params.tf
py2tf/templates/module_wrapper.tf
py2tf/templates/variable.tfvars
tests/__init__.py
tests/test_jinja.py
tests/test_markdown.py
py2tf-0.4.4.dist-info/LICENSE
py2tf-0.4.4.dist-info/METADATA
py2tf-0.4.4.dist-info/WHEEL
py2tf-0.4.4.dist-info/entry_points.txt
py2tf-0.4.4.dist-info/top_level.txt
py2tf-0.4.4.dist-info/RECORD
