Metadata-Version: 2.1
Name: py2tf
Version: 0.4.4
Summary: Convert Pydantic Models into Terraform Variables
License: MIT
License-File: LICENSE
Requires-Dist: pydantic
Requires-Dist: typer
Requires-Dist: jinja2
Requires-Dist: glom
Requires-Dist: py-markdown-table
Provides-Extra: dev
Requires-Dist: black ; extra == 'dev'
Requires-Dist: build ; extra == 'dev'
Requires-Dist: glom ; extra == 'dev'
Requires-Dist: isort ; extra == 'dev'
Requires-Dist: mypy ; extra == 'dev'
Requires-Dist: pytest ; extra == 'dev'
Requires-Dist: pytest-cov ; extra == 'dev'
Requires-Dist: versioneer ; extra == 'dev'
